flashai/__init__.py
flashai-0.0.1.dist-info/METADATA
flashai-0.0.1.dist-info/WHEEL
flashai-0.0.1.dist-info/licenses/LICENSE
flashai-0.0.1.dist-info/RECORD
